sample_tests/__init__.py
sample_tests/amidar_enemy_removal.py
sample_tests/amidar_gang_up.py
sample_tests/amidar_movement.py
sample_tests/amidar_tests.py
sample_tests/breakout_ez_channel.py
sample_tests/breakout_last_brick.py
sample_tests/breakout_polar_angles.py
sample_tests/breakout_tests.py
sample_tests/space_invaders_no_shields.py
sample_tests/space_invaders_randomness.py
sample_tests/space_invaders_shield_xs.py
test/__init__.py
test/benchmark.py
toybox_envs/__init__.py
toybox_envs/amidar.py
toybox_envs/base.py
toybox_envs/breakout.py
toybox_envs/constants.py
toybox_envs/gridworld.py
toybox_envs/space_invaders.py
toybox_envs/atari/__init__.py
toybox_envs/atari/amidar.py
toybox_envs/atari/base.py
toybox_envs/atari/breakout.py
toybox_envs/atari/constants.py
toybox_envs/atari/gridworld.py
toybox_envs/atari/space_invaders.py
toybox_envs-0.2.0.dist-info/METADATA
toybox_envs-0.2.0.dist-info/WHEEL
toybox_envs-0.2.0.dist-info/top_level.txt
toybox_envs-0.2.0.dist-info/RECORD
